cbm_cpp.cp38-win_amd64.pyd
cbm/CBM.py
cbm/__init__.py
cbm/_version.py
cyclicbm-0.0.9.data/headers/cbm.h
cyclicbm-0.0.9.data/headers/pycbm.h
cyclicbm-0.0.9.dist-info/LICENSE
cyclicbm-0.0.9.dist-info/METADATA
cyclicbm-0.0.9.dist-info/WHEEL
cyclicbm-0.0.9.dist-info/top_level.txt
cyclicbm-0.0.9.dist-info/RECORD
