Metadata-Version: 2.1
Name: cyclicbm
Version: 0.0.9
Summary: Cyclic Boosting Machines
Home-page: https://github.com/Microsoft/CBM
Author: Markus Cozowicz
Author-email: marcozo@microsoft.com
License: MIT
Platform: UNKNOWN
Classifier: Development Status :: 4 - Beta
Classifier: License :: OSI Approved :: MIT License
Classifier: Programming Language :: Python :: 3.6
Classifier: Programming Language :: Python :: 3.7
Classifier: Programming Language :: Python :: 3.8
Classifier: Intended Audience :: Developers
Classifier: Intended Audience :: Science/Research
Classifier: Topic :: Scientific/Engineering :: Mathematics
License-File: LICENSE
Requires-Dist: pybind11 (>=2.2)
Requires-Dist: numpy
Requires-Dist: scikit-learn
Requires-Dist: pandas
Provides-Extra: interactive
Requires-Dist: matplotlib (>=2.2.0) ; extra == 'interactive'
